facere_sensum/__init__.py
facere_sensum/fs.py
facere_sensum/connectors/__init__.py
facere_sensum/connectors/customsearch.py
facere_sensum/connectors/uplevel.py
facere_sensum/connectors/uptodate.py
facere_sensum/connectors/user.py
facere_sensum/connectors/GitHub/_github.py
facere_sensum/connectors/GitHub/fork.py
facere_sensum/connectors/GitHub/star.py
facere_sensum/connectors/GitHub/watch.py
facere_sensum-0.0.5.dist-info/METADATA
facere_sensum-0.0.5.dist-info/WHEEL
facere_sensum-0.0.5.dist-info/entry_points.txt
facere_sensum-0.0.5.dist-info/licenses/LICENSE
facere_sensum-0.0.5.dist-info/RECORD
