Metadata-Version: 2.3
Name: facere-sensum
Version: 0.0.5
Summary: facere-sensum: make sense of the turmoil
Project-URL: Homepage, https://github.com/lunarserge/facere-sensum
Project-URL: Bug Tracker, https://github.com/lunarserge/facere-sensum/issues
Author: Serge Lunev
License-File: LICENSE
Classifier: License :: OSI Approved :: MIT License
Classifier: Operating System :: OS Independent
Classifier: Programming Language :: Python :: 3
Requires-Python: >=3.11
Requires-Dist: google-api-python-client>=2.93.0
Requires-Dist: matplotlib>=3.8.0
Requires-Dist: numpy>=1.24.3
Requires-Dist: pandas>=2.0.1
Requires-Dist: prettytable>=3.9.0
Requires-Dist: pygithub>=1.59.1
